[{"name":"Andreas Abele","href":"https:\/\/www.naturkundemuseum.berlin\/de\/einblicke\/mitarbeiter\/andreas.abele"},{"name":"Martin Aberhan","href":"https:\/\/www.naturkundemuseum.berlin\/de\/einblicke\/mitarbeiter\/martin.aberhan"},{"name":"Gaia Agnello","href":"https:\/\/www.naturkundemuseum.berlin\/de\/einblicke\/mitarbeiter\/gaia.agnello"},{"name":"Manfred Asche","href":"https:\/\/www.naturkundemuseum.berlin\/de\/einblicke\/mitarbeiter\/manfred.asche"},{"name":"Vera Assis Fernandes","href":"https:\/\/www.naturkundemuseum.berlin\/de\/einblicke\/mitarbeiter\/vera.fernandes"},{"name":"D\u00f6rte Badock","href":"https:\/\/www.naturkundemuseum.berlin\/de\/einblicke\/mitarbeiter\/doerte.badock"},{"name":"Kersten Barth","href":"https:\/\/www.naturkundemuseum.berlin\/de\/einblicke\/mitarbeiter\/kersten.barth"},{"name":"Peter Bartsch","href":"https:\/\/www.naturkundemuseum.berlin\/de\/einblicke\/mitarbeiter\/peter.bartsch"},{"name":"Manuela Bauche","href":"https:\/\/www.naturkundemuseum.berlin\/de\/einblicke\/mitarbeiter\/manuela.bauche"},{"name":"Emma Berdan","href":"https:\/\/www.naturkundemuseum.berlin\/de\/einblicke\/mitarbeiter\/emma.berdan"},{"name":"Lutz Berner","href":"https:\/\/www.naturkundemuseum.berlin\/de\/einblicke\/mitarbeiter\/lutz.berner"},{"name":"Faysal Bibi","href":"https:\/\/www.naturkundemuseum.berlin\/de\/einblicke\/mitarbeiter\/faysal.bibi"},{"name":"Constanze Bickelmann","href":"https:\/\/www.naturkundemuseum.berlin\/de\/einblicke\/mitarbeiter\/constanze.bickelmann"},{"name":"Annett Billepp","href":"https:\/\/www.naturkundemuseum.berlin\/de\/einblicke\/mitarbeiter\/annett.billepp"},{"name":"Steffen Bock","href":"https:\/\/www.naturkundemuseum.berlin\/de\/einblicke\/mitarbeiter\/steffen.bock"},{"name":"Denise Bode","href":"https:\/\/www.naturkundemuseum.berlin\/de\/einblicke\/mitarbeiter\/denise.bode"},{"name":"Gottfried B\u00f6hme","href":"https:\/\/www.naturkundemuseum.berlin\/de\/einblicke\/mitarbeiter\/gottfried.boehme"},{"name":"Kirsten Born","href":"https:\/\/www.naturkundemuseum.berlin\/de\/einblicke\/mitarbeiter\/kirsten.born"},{"name":"Vivien Bothe","href":"https:\/\/www.naturkundemuseum.berlin\/de\/einblicke\/mitarbeiter\/vivien.bothe"},{"name":"Markus Brinkmann","href":"https:\/\/www.naturkundemuseum.berlin\/de\/einblicke\/mitarbeiter\/markus.brinkmann"},{"name":"Regina Br\u00fcckner","href":"https:\/\/www.naturkundemuseum.berlin\/de\/einblicke\/mitarbeiter\/regina.brueckner"},{"name":"Alexander Buhl","href":"https:\/\/www.naturkundemuseum.berlin\/de\/einblicke\/mitarbeiter\/alexander.buhl"},{"name":"Sonja Calvus","href":"https:\/\/www.naturkundemuseum.berlin\/de\/einblicke\/mitarbeiter\/sonja.calvus"},{"name":"Alice Chodura","href":"https:\/\/www.naturkundemuseum.berlin\/de\/einblicke\/mitarbeiter\/alice.chodura"},{"name":"Charles Oliver Coleman","href":"https:\/\/www.naturkundemuseum.berlin\/de\/einblicke\/mitarbeiter\/oliver.coleman"},{"name":"Peter Czaja","href":"https:\/\/www.naturkundemuseum.berlin\/de\/einblicke\/mitarbeiter\/peter.czaja"},{"name":"Ferdinand Damaschun","href":"https:\/\/www.naturkundemuseum.berlin\/de\/einblicke\/mitarbeiter\/ferdinand.damaschun"},{"name":"Katrin Damrau","href":"https:\/\/www.naturkundemuseum.berlin\/de\/einblicke\/mitarbeiter\/katrin.damrau"},{"name":"Marylene Danto","href":"https:\/\/www.naturkundemuseum.berlin\/de\/einblicke\/mitarbeiter\/marylene.danto"},{"name":"J\u00fcrgen Deckert","href":"https:\/\/www.naturkundemuseum.berlin\/de\/einblicke\/mitarbeiter\/juergen.deckert"},{"name":"Lea Devaere","href":"https:\/\/www.naturkundemuseum.berlin\/de\/einblicke\/mitarbeiter\/lea.devaere"},{"name":"Julia Diekaemper","href":"https:\/\/www.naturkundemuseum.berlin\/de\/einblicke\/mitarbeiter\/julia.diekaemper"},{"name":"Carolin Dittrich","href":"https:\/\/www.naturkundemuseum.berlin\/de\/einblicke\/mitarbeiter\/carolin.dittrich"},{"name":"Bernd Domning","href":"https:\/\/www.naturkundemuseum.berlin\/de\/einblicke\/mitarbeiter\/bernd.domning"},{"name":"Wolfram Donath","href":"https:\/\/www.naturkundemuseum.berlin\/de\/einblicke\/mitarbeiter\/wolfram.donath"},{"name":"Thorleif D\u00f6rfel","href":"https:\/\/www.naturkundemuseum.berlin\/de\/einblicke\/mitarbeiter\/thorleif.doerfel"},{"name":"Sanja Drakulic","href":"https:\/\/www.naturkundemuseum.berlin\/de\/einblicke\/mitarbeiter\/sanja.drakulic"},{"name":"Jason Dunlop","href":"https:\/\/www.naturkundemuseum.berlin\/de\/einblicke\/mitarbeiter\/jason.dunlop"},{"name":"Petra Ebber","href":"https:\/\/www.naturkundemuseum.berlin\/de\/einblicke\/mitarbeiter\/petra.ebber"},{"name":"Pascal Eckhoff","href":"https:\/\/www.naturkundemuseum.berlin\/de\/einblicke\/mitarbeiter\/pascal.eckhoff"},{"name":"Michaela Engel","href":"https:\/\/www.naturkundemuseum.berlin\/de\/einblicke\/mitarbeiter\/michaela.engel"},{"name":"Benedikt Esch","href":"https:\/\/www.naturkundemuseum.berlin\/de\/einblicke\/mitarbeiter\/benedikt.esch"},{"name":"Astrid Faber","href":"https:\/\/www.naturkundemuseum.berlin\/de\/einblicke\/mitarbeiter\/astrid.faber"},{"name":"Marianne Falk","href":"https:\/\/www.naturkundemuseum.berlin\/de\/einblicke\/mitarbeiter\/marianne.falk"},{"name":"J\u00fcrgen Fiebig","href":"https:\/\/www.naturkundemuseum.berlin\/de\/einblicke\/mitarbeiter\/juergen.fiebig"},{"name":"Sylke Frahnert","href":"https:\/\/www.naturkundemuseum.berlin\/de\/einblicke\/mitarbeiter\/sylke.frahnert"},{"name":"Anja Friederichs","href":"https:\/\/www.naturkundemuseum.berlin\/de\/einblicke\/mitarbeiter\/anja.friederichs"},{"name":"Johannes Frisch","href":"https:\/\/www.naturkundemuseum.berlin\/de\/einblicke\/mitarbeiter\/johannes.frisch"},{"name":"Wolfram Fritzsch","href":"https:\/\/www.naturkundemuseum.berlin\/de\/einblicke\/mitarbeiter\/wolfram.fritzsch"},{"name":"J\u00f6rg Fr\u00f6bisch","href":"https:\/\/www.naturkundemuseum.berlin\/de\/einblicke\/mitarbeiter\/joerg.froebisch"},{"name":"Nadia Fr\u00f6bisch","href":"https:\/\/www.naturkundemuseum.berlin\/de\/einblicke\/mitarbeiter\/nadia.froebisch"},{"name":"Karl-Heinz Frommolt","href":"https:\/\/www.naturkundemuseum.berlin\/de\/einblicke\/mitarbeiter\/karl-heinz.frommolt"},{"name":"Christiane Funk","href":"https:\/\/www.naturkundemuseum.berlin\/de\/einblicke\/mitarbeiter\/christiane.funk"},{"name":"Nina Furchheim","href":"https:\/\/www.naturkundemuseum.berlin\/de\/einblicke\/mitarbeiter\/nina.furchheim"},{"name":"Linda Galle","href":"https:\/\/www.naturkundemuseum.berlin\/de\/einblicke\/mitarbeiter\/linda.galle"},{"name":"Saskia Gennrich","href":"https:\/\/www.naturkundemuseum.berlin\/de\/einblicke\/mitarbeiter\/s.gennrich"},{"name":"Peter Giere","href":"https:\/\/www.naturkundemuseum.berlin\/de\/einblicke\/mitarbeiter\/peter.giere"},{"name":"Nora Glaubrecht","href":"https:\/\/www.naturkundemuseum.berlin\/de\/einblicke\/mitarbeiter\/nora.glaubrecht"},{"name":"Falko Gl\u00f6ckler","href":"https:\/\/www.naturkundemuseum.berlin\/de\/einblicke\/mitarbeiter\/falko.gloeckler"},{"name":"Andreas Gnensch","href":"https:\/\/www.naturkundemuseum.berlin\/de\/einblicke\/mitarbeiter\/andreas.gnensch"},{"name":"Claudia G\u00f6bel","href":"https:\/\/www.naturkundemuseum.berlin\/de\/einblicke\/mitarbeiter\/claudia.goebel"},{"name":"Antje Goldau","href":"https:\/\/www.naturkundemuseum.berlin\/de\/einblicke\/mitarbeiter\/antje.goldau"},{"name":"Hwaja G\u00f6tz","href":"https:\/\/www.naturkundemuseum.berlin\/de\/einblicke\/mitarbeiter\/hwaja.goetz"},{"name":"Ansgar Greshake","href":"https:\/\/www.naturkundemuseum.berlin\/de\/einblicke\/mitarbeiter\/ansgar.greshake"},{"name":"Petra Grimm","href":"https:\/\/www.naturkundemuseum.berlin\/de\/einblicke\/mitarbeiter\/petra.grimm"},{"name":"Susanne Grube","href":"https:\/\/www.naturkundemuseum.berlin\/de\/einblicke\/mitarbeiter\/susanne.grube"},{"name":"Ulrike Grunow","href":"https:\/\/www.naturkundemuseum.berlin\/de\/einblicke\/mitarbeiter\/ulrike.grunow"},{"name":"Nicole G\u00fcldemeister","href":"https:\/\/www.naturkundemuseum.berlin\/de\/einblicke\/mitarbeiter\/nicole.gueldemeister"},{"name":"Linus G\u00fcnther","href":"https:\/\/www.naturkundemuseum.berlin\/de\/einblicke\/mitarbeiter\/linus.guenther"},{"name":"Rainer G\u00fcnther","href":"https:\/\/www.naturkundemuseum.berlin\/de\/einblicke\/mitarbeiter\/rainer.guenther"},{"name":"Astrid Hackel","href":"https:\/\/www.naturkundemuseum.berlin\/de\/einblicke\/mitarbeiter\/astrid.hackel"},{"name":"Sabine Hackethal","href":"https:\/\/www.naturkundemuseum.berlin\/de\/einblicke\/mitarbeiter\/sabine.hackethal"},{"name":"Holger Hackmann","href":"https:\/\/www.naturkundemuseum.berlin\/de\/einblicke\/mitarbeiter\/holger.hackmann"},{"name":"Gregor Hagedorn","href":"https:\/\/www.naturkundemuseum.berlin\/de\/einblicke\/mitarbeiter\/gregor.hagedorn"},{"name":"Oliver H\u00e4hnel","href":"https:\/\/www.naturkundemuseum.berlin\/de\/einblicke\/mitarbeiter\/oliver.haehnel"},{"name":"Alexandra Hamann","href":"https:\/\/www.naturkundemuseum.berlin\/de\/einblicke\/mitarbeiter\/alexandra.hamann"},{"name":"Christopher Hamann","href":"https:\/\/www.naturkundemuseum.berlin\/de\/einblicke\/mitarbeiter\/christopher.hamann"},{"name":"Corinna Hammer","href":"https:\/\/www.naturkundemuseum.berlin\/de\/einblicke\/mitarbeiter\/corinna.hammer"},{"name":"Oliver Hampe","href":"https:\/\/www.naturkundemuseum.berlin\/de\/einblicke\/mitarbeiter\/oliver.hampe"},{"name":"Allyne Hartmann","href":"https:\/\/www.naturkundemuseum.berlin\/de\/einblicke\/mitarbeiter\/allyne.hartmann"},{"name":"Viktor Hartung","href":"https:\/\/www.naturkundemuseum.berlin\/de\/einblicke\/mitarbeiter\/viktor.hartung"},{"name":"Thekla Hauer","href":"https:\/\/www.naturkundemuseum.berlin\/de\/einblicke\/mitarbeiter\/thekla.hauer"},{"name":"Angelika Haufe","href":"https:\/\/www.naturkundemuseum.berlin\/de\/einblicke\/mitarbeiter\/angelika.haufe"},{"name":"Christoph H\u00e4user","href":"https:\/\/www.naturkundemuseum.berlin\/de\/einblicke\/mitarbeiter\/christoph.haeuser"},{"name":"Lutz Hecht","href":"https:\/\/www.naturkundemuseum.berlin\/de\/einblicke\/mitarbeiter\/lutz.hecht"},{"name":"Carmen Heilmaier","href":"https:\/\/www.naturkundemuseum.berlin\/de\/einblicke\/mitarbeiter\/carmen.heilmaier"},{"name":"Nadja Heinisch","href":"https:\/\/www.naturkundemuseum.berlin\/de\/einblicke\/mitarbeiter\/nadja.heinisch"},{"name":"Valentin Henning","href":"https:\/\/www.naturkundemuseum.berlin\/de\/einblicke\/mitarbeiter\/valentin.henning"},{"name":"Anita Hermannst\u00e4dter","href":"https:\/\/www.naturkundemuseum.berlin\/de\/einblicke\/mitarbeiter\/a.hermannstaedter"},{"name":"Franziska Heuer","href":"https:\/\/www.naturkundemuseum.berlin\/de\/einblicke\/mitarbeiter\/franziska.heuer"},{"name":"Ina Heumann","href":"https:\/\/www.naturkundemuseum.berlin\/de\/einblicke\/mitarbeiter\/ina.heumann"},{"name":"Leon Hilgers","href":"https:\/\/www.naturkundemuseum.berlin\/de\/einblicke\/mitarbeiter\/leon.hilgers"},{"name":"Cornelia Hiller","href":"https:\/\/www.naturkundemuseum.berlin\/de\/einblicke\/mitarbeiter\/cornelia.hiller"},{"name":"Christy Hipsley","href":"https:\/\/www.naturkundemuseum.berlin\/de\/einblicke\/mitarbeiter\/christy.hipsley"},{"name":"Hannelore Hoch","href":"https:\/\/www.naturkundemuseum.berlin\/de\/einblicke\/mitarbeiter\/hannelore.hoch"},{"name":"Anke Hoffmann","href":"https:\/\/www.naturkundemuseum.berlin\/de\/einblicke\/mitarbeiter\/anke.hoffmann"},{"name":"Jana Hoffmann","href":"https:\/\/www.naturkundemuseum.berlin\/de\/einblicke\/mitarbeiter\/jana.hoffmann"},{"name":"Richard Hofmann","href":"https:\/\/www.naturkundemuseum.berlin\/de\/einblicke\/mitarbeiter\/richard.hofmann"},{"name":"Claudia H\u00f6mberg","href":"https:\/\/www.naturkundemuseum.berlin\/de\/einblicke\/mitarbeiter\/claudia.hoemberg"},{"name":"Jessica H\u00fcbner","href":"https:\/\/www.naturkundemuseum.berlin\/de\/einblicke\/mitarbeiter\/jessica.huebner"},{"name":"J\u00fcrgen Jabs","href":"https:\/\/www.naturkundemuseum.berlin\/de\/einblicke\/mitarbeiter\/juergen.jabs"},{"name":"Bernd J\u00e4ger","href":"https:\/\/www.naturkundemuseum.berlin\/de\/einblicke\/mitarbeiter\/bernd.jaeger"},{"name":"Lisa Jahn","href":"https:\/\/www.naturkundemuseum.berlin\/de\/einblicke\/mitarbeiter\/lisa.jahn"},{"name":"Stephan Junker","href":"https:\/\/www.naturkundemuseum.berlin\/de\/einblicke\/mitarbeiter\/stephan.junker"},{"name":"Claudia Kaatz","href":"https:\/\/www.naturkundemuseum.berlin\/de\/einblicke\/mitarbeiter\/claudia.kaatz"},{"name":"Nina Kaiser","href":"https:\/\/www.naturkundemuseum.berlin\/de\/einblicke\/mitarbeiter\/nina.kaiser"},{"name":"Christian Kammerer","href":"https:\/\/www.naturkundemuseum.berlin\/de\/einblicke\/mitarbeiter\/christian.kammerer"},{"name":"Angelika K\u00e4mpf","href":"https:\/\/www.naturkundemuseum.berlin\/de\/einblicke\/mitarbeiter\/angelika.kaempf"},{"name":"Kristine K\u00e4mpf","href":"https:\/\/www.naturkundemuseum.berlin\/de\/einblicke\/mitarbeiter\/kristine.kaempf"},{"name":"Felix Kaufmann","href":"https:\/\/www.naturkundemuseum.berlin\/de\/einblicke\/mitarbeiter\/felix.kaufmann"},{"name":"Silvia Keinath","href":"https:\/\/www.naturkundemuseum.berlin\/de\/einblicke\/mitarbeiter\/silvia.keinath"},{"name":"Omid Khorramshahi","href":"https:\/\/www.naturkundemuseum.berlin\/de\/einblicke\/mitarbeiter\/omid.khorramshahi"},{"name":"Wolfgang Kiessling","href":"https:\/\/www.naturkundemuseum.berlin\/de\/einblicke\/mitarbeiter\/wolfgang.kiessling"},{"name":"Sebastian Kirchhof","href":"https:\/\/www.naturkundemuseum.berlin\/de\/einblicke\/mitarbeiter\/sebastian.kirchhof"},{"name":"Martin Kirchner","href":"https:\/\/www.naturkundemuseum.berlin\/de\/einblicke\/mitarbeiter\/martin.kirchner"},{"name":"Lukas Kirschey","href":"https:\/\/www.naturkundemuseum.berlin\/de\/einblicke\/mitarbeiter\/lukas.kirschey"},{"name":"Carina Klein","href":"https:\/\/www.naturkundemuseum.berlin\/de\/einblicke\/mitarbeiter\/carina.klein"},{"name":"Tomas Kleinert","href":"https:\/\/www.naturkundemuseum.berlin\/de\/einblicke\/mitarbeiter\/tomas.kleinert"},{"name":"Lisa Kluckert","href":"https:\/\/www.naturkundemuseum.berlin\/de\/einblicke\/mitarbeiter\/lisa.kluckert"},{"name":"Klaus Klups","href":"https:\/\/www.naturkundemuseum.berlin\/de\/einblicke\/mitarbeiter\/klaus.klups"},{"name":"Silke Knippert","href":"https:\/\/www.naturkundemuseum.berlin\/de\/einblicke\/mitarbeiter\/silke.knippert"},{"name":"Hans-Rudolf Kn\u00f6fler","href":"https:\/\/www.naturkundemuseum.berlin\/de\/einblicke\/mitarbeiter\/hans-rudolf.knoefler"},{"name":"Frank Koch","href":"https:\/\/www.naturkundemuseum.berlin\/de\/einblicke\/mitarbeiter\/frank.koch"},{"name":"G\u00fcnther Korb","href":"https:\/\/www.naturkundemuseum.berlin\/de\/einblicke\/mitarbeiter\/guenther.korb"},{"name":"Dieter Korn","href":"https:\/\/www.naturkundemuseum.berlin\/de\/einblicke\/mitarbeiter\/dieter.korn"},{"name":"Alice Kracht","href":"https:\/\/www.naturkundemuseum.berlin\/de\/einblicke\/mitarbeiter\/alice.kracht"},{"name":"Kathrin Krahn","href":"https:\/\/www.naturkundemuseum.berlin\/de\/einblicke\/mitarbeiter\/kathrin.krahn"},{"name":"Stefanie Krause","href":"https:\/\/www.naturkundemuseum.berlin\/de\/einblicke\/mitarbeiter\/stefanie.krause"},{"name":"Melanie Krauth","href":"https:\/\/www.naturkundemuseum.berlin\/de\/einblicke\/mitarbeiter\/melanie.krauth"},{"name":"Sonja Kreft","href":"https:\/\/www.naturkundemuseum.berlin\/de\/einblicke\/mitarbeiter\/sonja.kreft"},{"name":"Ilona Kr\u00fcger","href":"https:\/\/www.naturkundemuseum.berlin\/de\/einblicke\/mitarbeiter\/ilona.krueger"},{"name":"Stefanie Krzyzniewski","href":"https:\/\/www.naturkundemuseum.berlin\/de\/einblicke\/mitarbeiter\/s.krzyzniewski"},{"name":"Andreas Kunkel","href":"https:\/\/www.naturkundemuseum.berlin\/de\/einblicke\/mitarbeiter\/andreas.kunkel"},{"name":"Leslie Kuo","href":"https:\/\/www.naturkundemuseum.berlin\/de\/einblicke\/mitarbeiter\/leslie.kuo"},{"name":"Hannelore Landsberg","href":"https:\/\/www.naturkundemuseum.berlin\/de\/einblicke\/mitarbeiter\/hannelore.landsberg"},{"name":"Mario Lasseck","href":"https:\/\/www.naturkundemuseum.berlin\/de\/einblicke\/mitarbeiter\/mario.lasseck"},{"name":"David Lazarus","href":"https:\/\/www.naturkundemuseum.berlin\/de\/einblicke\/mitarbeiter\/david.lazarus"},{"name":"Lucyna Leda","href":"https:\/\/www.naturkundemuseum.berlin\/de\/einblicke\/mitarbeiter\/lucyna.leda"},{"name":"Erik Lehmann","href":"https:\/\/www.naturkundemuseum.berlin\/de\/einblicke\/mitarbeiter\/erik.lehmann"},{"name":"Hans-J\u00fcrgen Lehmann","href":"https:\/\/www.naturkundemuseum.berlin\/de\/einblicke\/mitarbeiter\/hans-juergen.lehmann"},{"name":"Nora Lentge-Maa\u00df","href":"https:\/\/www.naturkundemuseum.berlin\/de\/einblicke\/mitarbeiter\/nora.maass"},{"name":"Doris Leue","href":"https:\/\/www.naturkundemuseum.berlin\/de\/einblicke\/mitarbeiter\/doris.leue"},{"name":"Anja Liehske","href":"https:\/\/www.naturkundemuseum.berlin\/de\/einblicke\/mitarbeiter\/anja.liehske"},{"name":"Steven Lischke","href":"https:\/\/www.naturkundemuseum.berlin\/de\/einblicke\/mitarbeiter\/steven.lischke"},{"name":"Volker Lohrmann","href":"https:\/\/www.naturkundemuseum.berlin\/de\/einblicke\/mitarbeiter\/volker.lohrmann"},{"name":"Soledad Luna","href":"https:\/\/www.naturkundemuseum.berlin\/de\/einblicke\/mitarbeiter\/soledad.luna"},{"name":"Carsten L\u00fcter","href":"https:\/\/www.naturkundemuseum.berlin\/de\/einblicke\/mitarbeiter\/carsten.lueter"},{"name":"Robert Luther","href":"https:\/\/www.naturkundemuseum.berlin\/de\/einblicke\/mitarbeiter\/robert.luther"},{"name":"Anne MacKinney","href":"https:\/\/www.naturkundemuseum.berlin\/de\/einblicke\/mitarbeiter\/anne.mckinney"},{"name":"Kristin Mahlow","href":"https:\/\/www.naturkundemuseum.berlin\/de\/einblicke\/mitarbeiter\/kristin.mahlow"},{"name":"Lothar Maitas","href":"https:\/\/www.naturkundemuseum.berlin\/de\/einblicke\/mitarbeiter\/lothar.maitas"},{"name":"Heinrich Mallison","href":"https:\/\/www.naturkundemuseum.berlin\/de\/einblicke\/mitarbeiter\/heinrich.mallison"},{"name":"Sven Marotzke","href":"https:\/\/www.naturkundemuseum.berlin\/de\/einblicke\/mitarbeiter\/sven.marotzke"},{"name":"Elena Martellato","href":"https:\/\/www.naturkundemuseum.berlin\/de\/einblicke\/mitarbeiter\/elena.martellato"},{"name":"Andre Mascarenhas","href":"https:\/\/www.naturkundemuseum.berlin\/de\/einblicke\/mitarbeiter\/andre.mascarenhas"},{"name":"Jens Matzekat","href":"https:\/\/www.naturkundemuseum.berlin\/de\/einblicke\/mitarbeiter\/jens.matzekat"},{"name":"Detlev Matzke","href":"https:\/\/www.naturkundemuseum.berlin\/de\/einblicke\/mitarbeiter\/detlev.matzke"},{"name":"Sabine Maurer","href":"https:\/\/www.naturkundemuseum.berlin\/de\/einblicke\/mitarbeiter\/sabine.maurer"},{"name":"Frieder Mayer","href":"https:\/\/www.naturkundemuseum.berlin\/de\/einblicke\/mitarbeiter\/frieder.mayer"},{"name":"Susan Mbedi","href":"https:\/\/www.naturkundemuseum.berlin\/de\/einblicke\/mitarbeiter\/susan.mbedi"},{"name":"Wolfram Mey","href":"https:\/\/www.naturkundemuseum.berlin\/de\/einblicke\/mitarbeiter\/wolfram.mey"},{"name":"Joanna Mitchell","href":"https:\/\/www.naturkundemuseum.berlin\/de\/einblicke\/mitarbeiter\/joanna.mitchell"},{"name":"Christian Mitgutsch","href":"https:\/\/www.naturkundemuseum.berlin\/de\/einblicke\/mitarbeiter\/christian.mitgutsch"},{"name":"Barbara Mohr","href":"https:\/\/www.naturkundemuseum.berlin\/de\/einblicke\/mitarbeiter\/barbara.mohr"},{"name":"Tanja Mohr-Westheide","href":"https:\/\/www.naturkundemuseum.berlin\/de\/einblicke\/mitarbeiter\/tanja.mohr-westheide"},{"name":"Uwe Moldrzyk","href":"https:\/\/www.naturkundemuseum.berlin\/de\/einblicke\/mitarbeiter\/uwe.moldrzyk"},{"name":"Alexandra Moormann","href":"https:\/\/www.naturkundemuseum.berlin\/de\/einblicke\/mitarbeiter\/alexandra.moormann"},{"name":"Johannes M\u00fcller","href":"https:\/\/www.naturkundemuseum.berlin\/de\/einblicke\/mitarbeiter\/johannes.mueller"},{"name":"Magdalena M\u00fcller","href":"https:\/\/www.naturkundemuseum.berlin\/de\/einblicke\/mitarbeiter\/magdalena.mueller"},{"name":"Mandy M\u00fcller","href":"https:\/\/www.naturkundemuseum.berlin\/de\/einblicke\/mitarbeiter\/mandy.mueller"},{"name":"Tahani Nadim","href":"https:\/\/www.naturkundemuseum.berlin\/de\/einblicke\/mitarbeiter\/tahani.nadim"},{"name":"Mirjam Nadjafzadeh","href":"https:\/\/www.naturkundemuseum.berlin\/de\/einblicke\/mitarbeiter\/mirjam.nadjafzadeh"},{"name":"Shahin Nawai","href":"https:\/\/www.naturkundemuseum.berlin\/de\/einblicke\/mitarbeiter\/shahin.nawai"},{"name":"Birger Neuhaus","href":"https:\/\/www.naturkundemuseum.berlin\/de\/einblicke\/mitarbeiter\/birger.neuhaus"},{"name":"Christian Neumann","href":"https:\/\/www.naturkundemuseum.berlin\/de\/einblicke\/mitarbeiter\/christian.neumann"},{"name":"Monika Neumann","href":"https:\/\/www.naturkundemuseum.berlin\/de\/einblicke\/mitarbeiter\/monika.neumann"},{"name":"Stephanie Niemeier","href":"https:\/\/www.naturkundemuseum.berlin\/de\/einblicke\/mitarbeiter\/stephanie.niemeier"},{"name":"Michael Ohl","href":"https:\/\/www.naturkundemuseum.berlin\/de\/einblicke\/mitarbeiter\/michael.ohl"},{"name":"Bernd Ollenschl\u00e4ger","href":"https:\/\/www.naturkundemuseum.berlin\/de\/einblicke\/mitarbeiter\/bernd.ollenschlaeger"},{"name":"Kerstin Pannhorst","href":"https:\/\/www.naturkundemuseum.berlin\/de\/einblicke\/mitarbeiter\/kerstin.pannhorst"},{"name":"Eva Patzschke","href":"https:\/\/www.naturkundemuseum.berlin\/de\/einblicke\/mitarbeiter\/eva.patzschke"},{"name":"Johannes Penner","href":"https:\/\/www.naturkundemuseum.berlin\/de\/einblicke\/mitarbeiter\/johannes.penner"},{"name":"Mareike Petersen","href":"https:\/\/www.naturkundemuseum.berlin\/de\/einblicke\/mitarbeiter\/mareike.petersen"},{"name":"Lisa Pettibone","href":"https:\/\/www.naturkundemuseum.berlin\/de\/einblicke\/mitarbeiter\/lisa.pettibone"},{"name":"Carla Pinho","href":"https:\/\/www.naturkundemuseum.berlin\/de\/einblicke\/mitarbeiter\/carla.pinho"},{"name":"Christoph Plappert","href":"https:\/\/www.naturkundemuseum.berlin\/de\/einblicke\/mitarbeiter\/christoph.plappert"},{"name":"J\u00f6rg Pl\u00f6tner","href":"https:\/\/www.naturkundemuseum.berlin\/de\/einblicke\/mitarbeiter\/joerg.ploetner"},{"name":"Irina Podgorny","href":"https:\/\/www.naturkundemuseum.berlin\/de\/einblicke\/mitarbeiter\/irina.podgorny"},{"name":"Jenny Pohl","href":"https:\/\/www.naturkundemuseum.berlin\/de\/einblicke\/mitarbeiter\/jenny.pohl"},{"name":"Catrin Puffert","href":"https:\/\/www.naturkundemuseum.berlin\/de\/einblicke\/mitarbeiter\/catrin.puffert"},{"name":"Christiane Quaisser","href":"https:\/\/www.naturkundemuseum.berlin\/de\/einblicke\/mitarbeiter\/christiane.quaisser"},{"name":"Hans-Ulrich Raake","href":"https:\/\/www.naturkundemuseum.berlin\/de\/einblicke\/mitarbeiter\/hans-ulrich.raake"},{"name":"Carola Radke","href":"https:\/\/www.naturkundemuseum.berlin\/de\/einblicke\/mitarbeiter\/carola.radke"},{"name":"Ulli Raschke","href":"https:\/\/www.naturkundemuseum.berlin\/de\/einblicke\/mitarbeiter\/ulli.raschke"},{"name":"Diane Raspe","href":"https:\/\/www.naturkundemuseum.berlin\/de\/einblicke\/mitarbeiter\/diane.raspe"},{"name":"Yvonne Reimers","href":"https:\/\/www.naturkundemuseum.berlin\/de\/einblicke\/mitarbeiter\/yvonne.reimers"},{"name":"Uwe Reimold","href":"https:\/\/www.naturkundemuseum.berlin\/de\/einblicke\/mitarbeiter\/uwe.reimold"},{"name":"Erik Reinholz","href":"https:\/\/www.naturkundemuseum.berlin\/de\/einblicke\/mitarbeiter\/erik.reinholz"},{"name":"Inna Reise","href":"https:\/\/www.naturkundemuseum.berlin\/de\/einblicke\/mitarbeiter\/inna.reise"},{"name":"Johan Renaudie","href":"https:\/\/www.naturkundemuseum.berlin\/de\/einblicke\/mitarbeiter\/johan.renaudie"},{"name":"Katrin Reuter","href":"https:\/\/www.naturkundemuseum.berlin\/de\/einblicke\/mitarbeiter\/katrin.reuter"},{"name":"Robert Richter","href":"https:\/\/www.naturkundemuseum.berlin\/de\/einblicke\/mitarbeiter\/robert.richter"},{"name":"Viola Richter","href":"https:\/\/www.naturkundemuseum.berlin\/de\/einblicke\/mitarbeiter\/viola.richter"},{"name":"Regina Rieck","href":"https:\/\/www.naturkundemuseum.berlin\/de\/einblicke\/mitarbeiter\/regina.rieck"},{"name":"Caroline Ring","href":"https:\/\/www.naturkundemuseum.berlin\/de\/einblicke\/mitarbeiter\/caroline.ring"},{"name":"Simon Ripperger","href":"https:\/\/www.naturkundemuseum.berlin\/de\/einblicke\/mitarbeiter\/simon.ripperger"},{"name":"Martina Ri\u00dfberger","href":"https:\/\/www.naturkundemuseum.berlin\/de\/einblicke\/mitarbeiter\/martina.rissberger"},{"name":"Mark-Oliver R\u00f6del","href":"https:\/\/www.naturkundemuseum.berlin\/de\/einblicke\/mitarbeiter\/mo.roedel"},{"name":"Juliane R\u00f6hner","href":"https:\/\/www.naturkundemuseum.berlin\/de\/einblicke\/mitarbeiter\/juliane.roehner"},{"name":"Wiebke R\u00f6ssig","href":"https:\/\/www.naturkundemuseum.berlin\/de\/einblicke\/mitarbeiter\/wiebke.roessig"},{"name":"Adele Rother","href":"https:\/\/www.naturkundemuseum.berlin\/de\/einblicke\/mitarbeiter\/adele.rother"},{"name":"Roberto Rozzi","href":"https:\/\/www.naturkundemuseum.berlin\/de\/einblicke\/mitarbeiter\/roberto.rozzi"},{"name":"Melanie R\u00fchl","href":"https:\/\/www.naturkundemuseum.berlin\/de\/einblicke\/mitarbeiter\/melanie.ruehl"},{"name":"Kerstin Runki","href":"https:\/\/www.naturkundemuseum.berlin\/de\/einblicke\/mitarbeiter\/kerstin.runki"},{"name":"Sylvia Salzmann","href":"https:\/\/www.naturkundemuseum.berlin\/de\/einblicke\/mitarbeiter\/sylvia.salzmann"},{"name":"Laura Sandberger-Loua","href":"https:\/\/www.naturkundemuseum.berlin\/de\/einblicke\/mitarbeiter\/laura.sandberger"},{"name":"Anke S\u00e4nger","href":"https:\/\/www.naturkundemuseum.berlin\/de\/einblicke\/mitarbeiter\/anke.saenger"},{"name":"Manuela Sann","href":"https:\/\/www.naturkundemuseum.berlin\/de\/einblicke\/mitarbeiter\/manuela.sann"},{"name":"Franziska Sattler","href":"https:\/\/www.naturkundemuseum.berlin\/de\/einblicke\/mitarbeiter\/franziska.sattler"},{"name":"Livia Sch\u00e4ffler","href":"https:\/\/www.naturkundemuseum.berlin\/de\/einblicke\/mitarbeiter\/livia.schaeffler"},{"name":"Holger Schick","href":"https:\/\/www.naturkundemuseum.berlin\/de\/einblicke\/mitarbeiter\/holger.schick"},{"name":"Rainer Schliep","href":"https:\/\/www.naturkundemuseum.berlin\/de\/einblicke\/mitarbeiter\/rainer.schliep"},{"name":"Thomas Schmid-Dankward","href":"https:\/\/www.naturkundemuseum.berlin\/de\/einblicke\/mitarbeiter\/t.schmid-dankward"},{"name":"Rita Schmidt","href":"https:\/\/www.naturkundemuseum.berlin\/de\/einblicke\/mitarbeiter\/rita.schmidt"},{"name":"Elisa Schmitt","href":"https:\/\/www.naturkundemuseum.berlin\/de\/einblicke\/mitarbeiter\/elisa.schmitt"},{"name":"Ralf-Thomas Schmitt","href":"https:\/\/www.naturkundemuseum.berlin\/de\/einblicke\/mitarbeiter\/ralf-thomas.schmitt"},{"name":"Susanne Schmitt","href":"https:\/\/www.naturkundemuseum.berlin\/de\/einblicke\/mitarbeiter\/susanne.schmitt"},{"name":"Isabel Schmuck","href":"https:\/\/www.naturkundemuseum.berlin\/de\/einblicke\/mitarbeiter\/isabel.schmuck"},{"name":"Hendryk Schneider","href":"https:\/\/www.naturkundemuseum.berlin\/de\/einblicke\/mitarbeiter\/hendryk.schneider"},{"name":"Andreas Schnock","href":"https:\/\/www.naturkundemuseum.berlin\/de\/einblicke\/mitarbeiter\/andreas.schnock"},{"name":"Martin Schobben","href":"https:\/\/www.naturkundemuseum.berlin\/de\/einblicke\/mitarbeiter\/martin.schobben"},{"name":"Marten Sch\u00f6le","href":"https:\/\/www.naturkundemuseum.berlin\/de\/einblicke\/mitarbeiter\/marten.schoele"},{"name":"Peter Sch\u00f6nefeld","href":"https:\/\/www.naturkundemuseum.berlin\/de\/einblicke\/mitarbeiter\/peter.schoenefeld"},{"name":"Sabine Sch\u00f6ppe","href":"https:\/\/www.naturkundemuseum.berlin\/de\/einblicke\/mitarbeiter\/sabine.schoeppe"},{"name":"Thomas Schossleitner","href":"https:\/\/www.naturkundemuseum.berlin\/de\/einblicke\/mitarbeiter\/t.schossleitner"},{"name":"Robert Schreiber","href":"https:\/\/www.naturkundemuseum.berlin\/de\/einblicke\/mitarbeiter\/robert.schreiber"},{"name":"Stephan Schultka","href":"https:\/\/www.naturkundemuseum.berlin\/de\/einblicke\/mitarbeiter\/stephan.schultka"},{"name":"Yori Schultka","href":"https:\/\/www.naturkundemuseum.berlin\/de\/einblicke\/mitarbeiter\/yori.schultka"},{"name":"Selina Schultze","href":"https:\/\/www.naturkundemuseum.berlin\/de\/einblicke\/mitarbeiter\/selina.schultze"},{"name":"Bernhard Schurian","href":"https:\/\/www.naturkundemuseum.berlin\/de\/einblicke\/mitarbeiter\/bernhard.schurian"},{"name":"Daniela Schwarz","href":"https:\/\/www.naturkundemuseum.berlin\/de\/einblicke\/mitarbeiter\/daniela.schwarz"},{"name":"Friederike Schwarz","href":"https:\/\/www.naturkundemuseum.berlin\/de\/einblicke\/mitarbeiter\/friederike.schwarz"},{"name":"Antje Schwiering","href":"https:\/\/www.naturkundemuseum.berlin\/de\/einblicke\/mitarbeiter\/antje.schwiering"},{"name":"Elke Siebert","href":"https:\/\/www.naturkundemuseum.berlin\/de\/einblicke\/mitarbeiter\/elke.siebert"},{"name":"Tanja Solak","href":"https:\/\/www.naturkundemuseum.berlin\/de\/einblicke\/mitarbeiter\/tanja.solak"},{"name":"Christian Sonntag","href":"https:\/\/www.naturkundemuseum.berlin\/de\/einblicke\/mitarbeiter\/christian.sonntag"},{"name":"Anne Stabler","href":"https:\/\/www.naturkundemuseum.berlin\/de\/einblicke\/mitarbeiter\/anne.stabler"},{"name":"Sven Stehle","href":"https:\/\/www.naturkundemuseum.berlin\/de\/einblicke\/mitarbeiter\/sven.stehle"},{"name":"Robert Stein","href":"https:\/\/www.naturkundemuseum.berlin\/de\/einblicke\/mitarbeiter\/robert.stein"},{"name":"Gesine Steiner","href":"https:\/\/www.naturkundemuseum.berlin\/de\/einblicke\/mitarbeiter\/gesine.steiner"},{"name":"Marlies Steininger","href":"https:\/\/www.naturkundemuseum.berlin\/de\/einblicke\/mitarbeiter\/marlies.steininger"},{"name":"Dieter St\u00f6ffler","href":"https:\/\/www.naturkundemuseum.berlin\/de\/einblicke\/mitarbeiter\/dieter.stoeffler"},{"name":"B\u00e4rbel Stripling","href":"https:\/\/www.naturkundemuseum.berlin\/de\/einblicke\/mitarbeiter\/baerbel.stripling"},{"name":"Ulrich Struck","href":"https:\/\/www.naturkundemuseum.berlin\/de\/einblicke\/mitarbeiter\/ulrich.struck"},{"name":"Ulrike Sturm","href":"https:\/\/www.naturkundemuseum.berlin\/de\/einblicke\/mitarbeiter\/ulrike.sturm"},{"name":"Jana Suchocka","href":"https:\/\/www.naturkundemuseum.berlin\/de\/einblicke\/mitarbeiter\/jana.suchocka"},{"name":"Lauren Sumner-Rooney","href":"https:\/\/www.naturkundemuseum.berlin\/de\/einblicke\/mitarbeiter\/lauren.sumner-rooney"},{"name":"Marco Tamborini","href":"https:\/\/www.naturkundemuseum.berlin\/de\/einblicke\/mitarbeiter\/marco.tamborini"},{"name":"Melanie Tietje","href":"https:\/\/www.naturkundemuseum.berlin\/de\/einblicke\/mitarbeiter\/melanie.tietje"},{"name":"Frank Tillack","href":"https:\/\/www.naturkundemuseum.berlin\/de\/einblicke\/mitarbeiter\/frank.tillack"},{"name":"Manuela Tilling","href":"https:\/\/www.naturkundemuseum.berlin\/de\/einblicke\/mitarbeiter\/manuela.tilling"},{"name":"Malte Timpte","href":"https:\/\/www.naturkundemuseum.berlin\/de\/einblicke\/mitarbeiter\/malte.timpte"},{"name":"Sandra Triepel","href":"https:\/\/www.naturkundemuseum.berlin\/de\/einblicke\/mitarbeiter\/sandra.triepel"},{"name":"Martin Tscholl","href":"https:\/\/www.naturkundemuseum.berlin\/de\/einblicke\/mitarbeiter\/martin.tscholl"},{"name":"Joshua Tyler","href":"https:\/\/www.naturkundemuseum.berlin\/de\/einblicke\/mitarbeiter\/joshua.tyler"},{"name":"Manfred Uhlig","href":"https:\/\/www.naturkundemuseum.berlin\/de\/einblicke\/mitarbeiter\/manfred.uhlig"},{"name":"Esther Ullrich-L\u00fcter","href":"https:\/\/www.naturkundemuseum.berlin\/de\/einblicke\/mitarbeiter\/e.ullrich-lueter"},{"name":"Luis Valente","href":"https:\/\/www.naturkundemuseum.berlin\/de\/einblicke\/mitarbeiter\/luis.valente"},{"name":"Bert Van Bocxlaer","href":"https:\/\/www.naturkundemuseum.berlin\/de\/einblicke\/mitarbeiter\/bert.vanbocxlaer"},{"name":"Collin Van Buren","href":"https:\/\/www.naturkundemuseum.berlin\/de\/einblicke\/mitarbeiter\/collin.vanburen"},{"name":"Johannes Vogel","href":"https:\/\/www.naturkundemuseum.berlin\/de\/einblicke\/mitarbeiter\/johannes.vogel"},{"name":"Philipp Vogt","href":"https:\/\/www.naturkundemuseum.berlin\/de\/einblicke\/mitarbeiter\/philipp.vogt"},{"name":"Katrin Vohland","href":"https:\/\/www.naturkundemuseum.berlin\/de\/einblicke\/mitarbeiter\/katrin.vohland"},{"name":"Matthias V\u00f6lker","href":"https:\/\/www.naturkundemuseum.berlin\/de\/einblicke\/mitarbeiter\/matthias.voelker"},{"name":"Swetlana Volland","href":"https:\/\/www.naturkundemuseum.berlin\/de\/einblicke\/mitarbeiter\/swetlana.volland"},{"name":"Manja Vo\u00df","href":"https:\/\/www.naturkundemuseum.berlin\/de\/einblicke\/mitarbeiter\/manja.voss"},{"name":"Kristina von Rintelen","href":"https:\/\/www.naturkundemuseum.berlin\/de\/einblicke\/mitarbeiter\/kristina.rintelen"},{"name":"Thomas von Rintelen","href":"https:\/\/www.naturkundemuseum.berlin\/de\/einblicke\/mitarbeiter\/thomas.rintelen"},{"name":"Ekkehard Wachmann","href":"https:\/\/www.naturkundemuseum.berlin\/de\/einblicke\/mitarbeiter\/ekkehard.wachmann"},{"name":"Imke Wardenburg","href":"https:\/\/www.naturkundemuseum.berlin\/de\/einblicke\/mitarbeiter\/imke.wardenburg"},{"name":"David Ware","href":"https:\/\/www.naturkundemuseum.berlin\/de\/einblicke\/mitarbeiter\/david.ware"},{"name":"Isabelle Waurick","href":"https:\/\/www.naturkundemuseum.berlin\/de\/einblicke\/mitarbeiter\/isabelle.waurick"},{"name":"Frank Wellmann","href":"https:\/\/www.naturkundemuseum.berlin\/de\/einblicke\/mitarbeiter\/frank.wellmann"},{"name":"Ingmar Werneburg","href":"https:\/\/www.naturkundemuseum.berlin\/de\/einblicke\/mitarbeiter\/ingmar.werneburg"},{"name":"Florian Wetzel","href":"https:\/\/www.naturkundemuseum.berlin\/de\/einblicke\/mitarbeiter\/florian.wetzel"},{"name":"Julia Wiedemann","href":"https:\/\/www.naturkundemuseum.berlin\/de\/einblicke\/mitarbeiter\/julia.wiedemann"},{"name":"Detlef Willborn","href":"https:\/\/www.naturkundemuseum.berlin\/de\/einblicke\/mitarbeiter\/detlef.willborn"},{"name":"Joachim Willers","href":"https:\/\/www.naturkundemuseum.berlin\/de\/einblicke\/mitarbeiter\/joachim.willers"},{"name":"Maraike Willsch","href":"https:\/\/www.naturkundemuseum.berlin\/de\/einblicke\/mitarbeiter\/maraike.willsch"},{"name":"Florian Witzmann","href":"https:\/\/www.naturkundemuseum.berlin\/de\/einblicke\/mitarbeiter\/florian.witzmann"},{"name":"Helga Wolf","href":"https:\/\/www.naturkundemuseum.berlin\/de\/einblicke\/mitarbeiter\/helga.wolf"},{"name":"Andrea Wolkenstein","href":"https:\/\/www.naturkundemuseum.berlin\/de\/einblicke\/mitarbeiter\/andrea.wolkenstein"},{"name":"Kai W\u00fcnnemann","href":"https:\/\/www.naturkundemuseum.berlin\/de\/einblicke\/mitarbeiter\/kai.wuennemann"},{"name":"Hiroshi Yamasaki","href":"https:\/\/www.naturkundemuseum.berlin\/de\/einblicke\/mitarbeiter\/hiroshi.yamasaki"},{"name":"Patrice Zaag","href":"https:\/\/www.naturkundemuseum.berlin\/de\/einblicke\/mitarbeiter\/patrice.zaag"},{"name":"Jutta Zeller","href":"https:\/\/www.naturkundemuseum.berlin\/de\/einblicke\/mitarbeiter\/jutta.zeller"},{"name":"David Ziegler","href":"https:\/\/www.naturkundemuseum.berlin\/de\/einblicke\/mitarbeiter\/david.ziegler"},{"name":"Joachim Ziegler","href":"https:\/\/www.naturkundemuseum.berlin\/de\/einblicke\/mitarbeiter\/joachim.ziegler"},{"name":"Mathias Zilch","href":"https:\/\/www.naturkundemuseum.berlin\/de\/einblicke\/mitarbeiter\/mathias.zilch"},{"name":"Christine Zorn","href":"https:\/\/www.naturkundemuseum.berlin\/de\/einblicke\/mitarbeiter\/christine.zorn"}]